pywrdgen/__init__.py
pywrdgen/__main__.py
pywrdgen/password.py
pywrdgen-0.1.0.dist-info/LICENSE
pywrdgen-0.1.0.dist-info/METADATA
pywrdgen-0.1.0.dist-info/WHEEL
pywrdgen-0.1.0.dist-info/entry_points.txt
pywrdgen-0.1.0.dist-info/top_level.txt
pywrdgen-0.1.0.dist-info/RECORD
